{"cameraMode":{"drawMode":0,"name":"Shaded","section":"Shading Mode"},"sceneLighting":false,"audioPlay":false,"sceneViewState":{"showFog":true,"showMaterialUpdate":false,"showSkybox":false,"showFlares":true,"showImageEffects":true,"showParticleSystems":true,"showVisualEffectGraphs":true,"m_FxEnabled":true},"in2DMode":false,"pivot":{"x":-4.300065994262695,"y":2.0189452171325685,"z":-0.13567233085632325},"rotation":{"x":-0.015514680184423924,"y":-0.9780941605567932,"z":0.19197532534599305,"w":-0.07911209762096405},"size":2.06113600730896,"orthographic":false}